comment/__init__.py
comment/admin.py
comment/apps.py
comment/checks.py
comment/context.py
comment/exceptions.py
comment/forms.py
comment/messages.py
comment/mixins.py
comment/responses.py
comment/urls.py
comment/utils.py
comment/validators.py
comment/api/__init__.py
comment/api/permissions.py
comment/api/serializers.py
comment/api/urls.py
comment/api/views.py
comment/conf/__init__.py
comment/conf/defaults.py
comment/locale/fa/LC_MESSAGES/django.po
comment/locale/fa/LC_MESSAGES/djangojs.po
comment/locale/hi/LC_MESSAGES/django.po
comment/locale/hi/LC_MESSAGES/djangojs.po
comment/locale/ja/LC_MESSAGES/django.po
comment/locale/ja/LC_MESSAGES/djangojs.po
comment/locale/test/LC_MESSAGES/django.po
comment/locale/test/LC_MESSAGES/djangojs.po
comment/managers/__init__.py
comment/managers/blocker.py
comment/managers/comments.py
comment/managers/flags.py
comment/managers/followers.py
comment/managers/reactions.py
comment/migrations/0001_initial.py
comment/migrations/0002_comment_edit_date.py
comment/migrations/0003_auto_20200419_1423.py
comment/migrations/0004_reaction_reactioninstance.py
comment/migrations/0005_auto_20200521_1301.py
comment/migrations/0006_flag_flaginstance.py
comment/migrations/0007_auto_20200620_1259.py
comment/migrations/0008_comment_urlhash.py
comment/migrations/0009_auto_20200811_1945.py
comment/migrations/0010_auto_20201023_1442.py
comment/migrations/0011_follower.py
comment/migrations/0012_blockeduser_blockeduserhistory.py
comment/migrations/__init__.py
comment/models/__init__.py
comment/models/blocker.py
comment/models/comments.py
comment/models/flags.py
comment/models/followers.py
comment/models/reactions.py
comment/service/__init__.py
comment/service/email.py
comment/signals/__init__.py
comment/signals/post_delete.py
comment/signals/post_migrate.py
comment/signals/post_save.py
comment/static/css/bootstrap-4.1.1.css
comment/static/css/comment.css
comment/static/img/default.png
comment/static/js/comment.js
comment/templates/comment/base.html
django_comments_dab-3.0.0.dist-info/METADATA
django_comments_dab-3.0.0.dist-info/WHEEL
django_comments_dab-3.0.0.dist-info/licenses/LICENSE
django_comments_dab-3.0.0.dist-info/RECORD
