Metadata-Version: 2.4
Name: django-comments-dab
Version: 3.0.0
Summary: Django Comment app. It can be associated with any given model.
Project-URL: Homepage, https://github.com/abhiabhi94/Comment
Project-URL: Documentation, https://comment.readthedocs.io/index.html
Project-URL: Source Code, https://github.com/abhiabhi94/Comment
Author-email: Radico <mus.radi85@gmail.com>
Maintainer-email: Radi Mustafa <mus.radi85@gmail.com>, Abhyudai <5ifocyqgf@relay.firefox.com>
License-Expression: MIT
License-File: LICENSE
Keywords: ajax,comment,comments,django
Classifier: Environment :: Web Environment
Classifier: Framework :: Django
Classifier: Framework :: Django :: 4.2
Classifier: Framework :: Django :: 5.0
Classifier: Framework :: Django :: 5.1
Classifier: Framework :: Django :: 5.2
Classifier: Intended Audience :: Developers
Classifier: License :: OSI Approved :: MIT License
Classifier: Operating System :: OS Independent
Classifier: Programming Language :: Python
Classifier: Programming Language :: Python :: 3.10
Classifier: Programming Language :: Python :: 3.11
Classifier: Programming Language :: Python :: 3.12
Classifier: Programming Language :: Python :: 3.13
Classifier: Topic :: Internet :: WWW/HTTP
Classifier: Topic :: Internet :: WWW/HTTP :: Dynamic Content
Requires-Python: >=3.10
Requires-Dist: django
Provides-Extra: markdown
Requires-Dist: markdown; extra == 'markdown'
